{
  "DOC": [
    {
      "id": "8232_COMMUN/PDF/SCH/0014.PDF",
      "filename": "8232_COMMUN_PDF_SCH_0014.PDF",
      "path": "https://cdn.asdh.aws.renault.com/SIE/WD/8232/media/WIRING/0014.pdf"
    },
    {
      "id": "8232_COMMUN/PDF/SCH/0015.PDF",
      "filename": "8232_COMMUN_PDF_SCH_0015.PDF",
      "path": "https://cdn.asdh.aws.renault.com/SIE/WD/8232/media/WIRING/0015.pdf"
    },
    {
      "id": "8232_COMMUN/PDF/SCH/0013.PDF",
      "filename": "8232_COMMUN_PDF_SCH_0013.PDF",
      "path": "https://cdn.asdh.aws.renault.com/SIE/WD/8232/media/WIRING/0013.pdf"
    }
  ]
}