{
  "PR": [
    {
      "id": "1247_811110",
      "filename": "1247_811110.svg",
      "path": "https://cdn.asdh.aws.renault.com/plate_illustrations/01013749.svg"
    },
    {
      "id": "1247_811010",
      "filename": "1247_811010.svg",
      "path": "https://cdn.asdh.aws.renault.com/plate_illustrations/01029513.svg"
    },
    {
      "id": "1247_811011",
      "filename": "1247_811011.svg",
      "path": "https://cdn.asdh.aws.renault.com/plate_illustrations/01026900.svg"
    },
    {
      "id": "1247_815010",
      "filename": "1247_815010.svg",
      "path": "https://cdn.asdh.aws.renault.com/plate_illustrations/01084329.svg"
    }
  ],
  "MR": [
    {
      "id": "0558",
      "filename": "Special notes Clio Renault Sport.pdf",
      "path": "https://cdn.asdh.aws.renault.com/SIE/MR_ASDE/Content/EN/0558.pdf"
    },
    {
      "id": "0583",
      "filename": "Special notes on CLIO V6 Phase II.pdf",
      "path": "https://cdn.asdh.aws.renault.com/SIE/MR_ASDE/Content/EN/0583.pdf"
    },
    {
      "id": "MR-337-CLIO-8",
      "filename": "M.R. 337 - 8 Electrical equipment phase 1.pdf",
      "path": "https://cdn.asdh.aws.renault.com/SIE/MR_ASDE/Content/EN/MR-337-CLIO-8.pdf"
    },
    {
      "id": "MR-338-CLIO-5",
      "filename": "M.R. 338 - 5 Mechanisms and Accessories phase 1.pdf",
      "path": "https://cdn.asdh.aws.renault.com/SIE/MR_ASDE/Content/EN/MR-338-CLIO-5.pdf"
    },
    {
      "id": "MR-345-CLIO-8",
      "filename": "M.R. 345 - 8 Electrical equipment phase 2.pdf",
      "path": "https://cdn.asdh.aws.renault.com/SIE/MR_ASDE/Content/EN/MR-345-CLIO-8.pdf"
    },
    {
      "id": "MR-338-CLIO-ADD",
      "filename": "M.R. 338 -5-7- ADD Features of vehicles from June 2001 phase 2.pdf",
      "path": "https://cdn.asdh.aws.renault.com/SIE/MR_ASDE/Content/EN/MR-338-CLIO-ADD.pdf"
    },
    {
      "id": "5af944d53ef64d00e0ef6017",
      "filename": "rear exterior lights : component parts location.xml",
      "path": "https://cdn.asdh.aws.renault.com/SIE/MR/Content/RDE-000428204.xml"
    },
    {
      "id": "5af585aac3da7a00dc229afe",
      "filename": "rear light bulb : removal - refitting.xml",
      "path": "https://cdn.asdh.aws.renault.com/SIE/MR/Content/RPR-000427460.xml"
    },
    {
      "id": "5af58619c3da7a00dc229b97",
      "filename": "3rd brake light : removal - refitting.xml",
      "path": "https://cdn.asdh.aws.renault.com/SIE/MR/Content/RPR-000427371.xml"
    },
    {
      "id": "5af5c3baf04d3300dc242d34",
      "filename": "license plate light : removal - refitting.xml",
      "path": "https://cdn.asdh.aws.renault.com/SIE/MR/Content/RPR-000428710.xml"
    }
  ],
  "MD": [
    {
      "id": "MR-432-X65-80D000",
      "filename": ".pdf",
      "path": "https://cdn.asdh.aws.renault.com/SIE/MD_B2/Content/EN/MR-432-X65-80D000.pdf"
    },
    {
      "id": "MR-432-X65-82D000",
      "filename": ".pdf",
      "path": "https://cdn.asdh.aws.renault.com/SIE/MD_B2/Content/EN/MR-432-X65-82D000.pdf"
    },
    {
      "id": "MR-346-CLIO-8",
      "filename": "M.R. 346 - 8 Electrical equipment.pdf",
      "path": "https://cdn.asdh.aws.renault.com/SIE/MD_B2/Content/EN/MR-346-CLIO-8.pdf"
    }
  ],
  "IMG": [
    {
      "id": "vignette",
      "filename": "vignette.png",
      "path": "https://cdn.asdh.aws.renault.com/nodes/N-21366.png"
    }
  ]
}